aldemsubs/__init__.py
aldemsubs/__main__.py
aldemsubs/aldemsubs.py
aldemsubs/config.py
aldemsubs/db.py
aldemsubs/feed.py
aldemsubs/utils.py
aldemsubs-0.1.3.data/scripts/aldemsubs
aldemsubs-0.1.3.dist-info/LICENSE
aldemsubs-0.1.3.dist-info/METADATA
aldemsubs-0.1.3.dist-info/WHEEL
aldemsubs-0.1.3.dist-info/top_level.txt
aldemsubs-0.1.3.dist-info/RECORD
