Metadata-Version: 2.1
Name: aldemsubs
Version: 0.1.3
Summary: Subscribe to Youtube channels via RSS
Home-page: https://gitlab.com/80KiloMett/aldemsubs
Author: Paul Hillmann - 80KiloMett
Author-email: 80kilomett@posteo.de
License: UNKNOWN
Platform: UNKNOWN
Classifier: Programming Language :: Python :: 3
Classifier: Programming Language :: Python :: 3.9
Classifier: License :: OSI Approved :: MIT License
Classifier: Operating System :: POSIX :: Linux
Requires-Python: >=3.7
Requires-Dist: feedparser
Requires-Dist: youtube-dl
Provides-Extra: dev
Requires-Dist: pytest ; extra == 'dev'
